functional_connectivity/__init__.py
functional_connectivity/_version.py
functional_connectivity/firstOrderMethods.py
functional_connectivity/fit.py
functional_connectivity/losses.py
functional_connectivity/models.py
functional_connectivity/generators/__init__.py
functional_connectivity/generators/graphical_model.py
functional_connectivity/inference/__init__.py
functional_connectivity/inference/base_graphical_lasso.py
functional_connectivity/readwrite/__init__.py
functional_connectivity/readwrite/dandi_handler.py
functional_connectivity/readwrite/data_handler.py
functional_connectivity/stats/__init__.py
functional_connectivity/stats/network_features.py
functional_connectivity/utils/__init__.py
functional_connectivity/utils/utils.py
functional_connectivity-0.1.3.dist-info/LICENSE
functional_connectivity-0.1.3.dist-info/METADATA
functional_connectivity-0.1.3.dist-info/WHEEL
functional_connectivity-0.1.3.dist-info/top_level.txt
functional_connectivity-0.1.3.dist-info/RECORD
