Metadata-Version: 2.1
Name: functional-connectivity
Version: 0.1.3
Summary: Sensing functional connectivity in the brain, in Python
Author-email: Tzu-Chi Yen <tzuchi.yen@colorado.edu>
License: GNU LESSER GENERAL PUBLIC LICENSE
Project-URL: repository, https://github.com/junipertcy/functional-connectivity
Project-URL: documentation, https://docs.netscied.tw/functional-connectivity/index.html
Keywords: functional-connectivity,convex-optimization,graphical-models
Classifier: Development Status :: 5 - Production/Stable
Classifier: Intended Audience :: Science/Research
Classifier: License :: OSI Approved :: GNU Lesser General Public License v3 (LGPLv3)
Classifier: Natural Language :: English
Classifier: Operating System :: Microsoft :: Windows
Classifier: Operating System :: POSIX
Classifier: Operating System :: Unix
Classifier: Operating System :: MacOS
Classifier: Programming Language :: Python :: 3.10
Classifier: Programming Language :: Python :: 3.11
Classifier: Programming Language :: Python :: 3.12
Classifier: Programming Language :: Python :: 3 :: Only
Classifier: Topic :: Scientific/Engineering
Classifier: Topic :: Software Development :: Libraries
Requires-Python: >=3.10
License-File: LICENSE
Requires-Dist: urllib3 >=1.26.9
Requires-Dist: matplotlib >=3.8.0
Requires-Dist: numpy >=1.26.1
Requires-Dist: scikit-learn >=1.3.2
Requires-Dist: numba >=0.58.1
Requires-Dist: loky >=3.4.1
Requires-Dist: xarray >=2023.10.1
Requires-Dist: jupyterlab >=4.0.7
Requires-Dist: nwbwidgets >=0.11.3
Requires-Dist: dandi >=0.58.1
Requires-Dist: h5py >=3.10.0
Requires-Dist: networkx >=3.2.1
Provides-Extra: dev
Requires-Dist: pytest >=7.4.3 ; extra == 'dev'
Requires-Dist: click >=8.1.7 ; extra == 'dev'
Requires-Dist: sphinx >=7.2.6 ; extra == 'dev'
